bigcommerce/__init__.py
bigcommerce/api.py
bigcommerce/connection.py
bigcommerce/customer_login_token.py
bigcommerce/exception.py
bigcommerce/resources/__init__.py
bigcommerce/resources/banners.py
bigcommerce/resources/base.py
bigcommerce/resources/blog_posts.py
bigcommerce/resources/brands.py
bigcommerce/resources/categories.py
bigcommerce/resources/countries.py
bigcommerce/resources/coupons.py
bigcommerce/resources/currencies.py
bigcommerce/resources/customer_groups.py
bigcommerce/resources/customers.py
bigcommerce/resources/gift_certificates.py
bigcommerce/resources/option_sets.py
bigcommerce/resources/options.py
bigcommerce/resources/order_statuses.py
bigcommerce/resources/orders.py
bigcommerce/resources/pages.py
bigcommerce/resources/payments.py
bigcommerce/resources/products.py
bigcommerce/resources/redirects.py
bigcommerce/resources/shipping.py
bigcommerce/resources/store.py
bigcommerce/resources/tax_classes.py
bigcommerce/resources/time.py
bigcommerce/resources/webhooks.py
tests/__init__.py
tests/test_api.py
tests/test_base.py
tests/test_connection.py
bigcommerce-0.23.4.dist-info/LICENSE.txt
bigcommerce-0.23.4.dist-info/METADATA
bigcommerce-0.23.4.dist-info/WHEEL
bigcommerce-0.23.4.dist-info/top_level.txt
bigcommerce-0.23.4.dist-info/RECORD
