Metadata-Version: 2.1
Name: bigcommerce
Version: 0.23.4
Summary: Connect Python applications with the Bigcommerce API
Home-page: https://github.com/bigcommerce/bigcommerce-api-python
Download-URL: https://pypi.python.org/packages/source/b/bigcommerce/bigcommerce-0.23.4.tar.gz
Author: Bigcommerce Engineering
Author-email: api@bigcommerce.com
License: MIT
Keywords: bigcommerce,api,v2,client
Classifier: Development Status :: 4 - Beta
Classifier: Topic :: Software Development :: Libraries :: Python Modules
Classifier: Topic :: Office/Business
Classifier: Topic :: Internet :: WWW/HTTP
Classifier: Intended Audience :: Developers
Classifier: License :: OSI Approved :: MIT License
Classifier: Programming Language :: Python
Classifier: Programming Language :: Python :: 3
Classifier: Programming Language :: Python :: 3.6
Classifier: Programming Language :: Python :: 3.7
Classifier: Programming Language :: Python :: 3.9
License-File: LICENSE.txt
Requires-Dist: requests>=2.25.1
Requires-Dist: pyjwt>=2.0.1
